{
  "generatedAt": "2026-02-28T06:06:28.767Z",
  "season": "2025-01",
  "clan": {
    "tag": "#JPRPRVUY",
    "name": "Akademia CoC PL",
    "clanLevel": 21
  },
  "league": {
    "tier": "Crystal League II",
    "group": 1
  },
  "groupPosition": 1,
  "state": "ended",
  "stats": {
    "warsPlayed": 7,
    "warsWon": 7,
    "warsLost": 0,
    "warsTied": 0,
    "stars": 254,
    "destruction": 612.8666666666667,
    "attacks": 103,
    "winRate": 100,
    "avgDefenseQuality": 35.18,
    "hardestToThreeCount": 5
  },
  "wars": [
    {
      "warTag": "JPRPRVUY-20250103T210849000Z",
      "startTime": "20250102T210849.000Z",
      "endTime": "20250103T210849.000Z",
      "teamSize": 15,
      "result": "win",
      "starsFor": 31,
      "starsAgainst": 24,
      "destructionFor": 83.53333333333333,
      "destructionAgainst": 62.333333333333336,
      "opponent": {
        "tag": "#PJC880J8",
        "name": "REAPER CREW",
        "clanLevel": 18
      }
    },
    {
      "warTag": "JPRPRVUY-20250104T211323000Z",
      "startTime": "20250103T211323.000Z",
      "endTime": "20250104T211323.000Z",
      "teamSize": 15,
      "result": "win",
      "starsFor": 40,
      "starsAgainst": 30,
      "destructionFor": 92.13333333333334,
      "destructionAgainst": 74.06666666666666,
      "opponent": {
        "tag": "#VVCGQ2QU",
        "name": "borgkelten",
        "clanLevel": 23
      }
    },
    {
      "warTag": "JPRPRVUY-20250105T212414000Z",
      "startTime": "20250104T212414.000Z",
      "endTime": "20250105T212414.000Z",
      "teamSize": 15,
      "result": "win",
      "starsFor": 33,
      "starsAgainst": 23,
      "destructionFor": 81,
      "destructionAgainst": 54.53333333333333,
      "opponent": {
        "tag": "#2LCCGVUCQ",
        "name": "Christ Is All",
        "clanLevel": 15
      }
    },
    {
      "warTag": "JPRPRVUY-20250106T213217000Z",
      "startTime": "20250105T213217.000Z",
      "endTime": "20250106T213217.000Z",
      "teamSize": 15,
      "result": "win",
      "starsFor": 33,
      "starsAgainst": 30,
      "destructionFor": 82.93333333333334,
      "destructionAgainst": 86.66666666666667,
      "opponent": {
        "tag": "#8QJ080YG",
        "name": "INMORTAL",
        "clanLevel": 18
      }
    },
    {
      "warTag": "JPRPRVUY-20250107T215704000Z",
      "startTime": "20250106T215704.000Z",
      "endTime": "20250107T215704.000Z",
      "teamSize": 15,
      "result": "win",
      "starsFor": 35,
      "starsAgainst": 29,
      "destructionFor": 86.26666666666667,
      "destructionAgainst": 73.66666666666667,
      "opponent": {
        "tag": "#2QVPYLG2U",
        "name": "ملوك الجن",
        "clanLevel": 16
      }
    },
    {
      "warTag": "JPRPRVUY-20250108T223447000Z",
      "startTime": "20250107T215714.000Z",
      "endTime": "20250108T223447.000Z",
      "teamSize": 15,
      "result": "win",
      "starsFor": 43,
      "starsAgainst": 10,
      "destructionFor": 98.6,
      "destructionAgainst": 26.333333333333332,
      "opponent": {
        "tag": "#2PG9PU82G",
        "name": "LOST F2P 2",
        "clanLevel": 18
      }
    },
    {
      "warTag": "JPRPRVUY-20250109T223446000Z",
      "startTime": "20250108T223446.000Z",
      "endTime": "20250109T223446.000Z",
      "teamSize": 15,
      "result": "win",
      "starsFor": 39,
      "starsAgainst": 25,
      "destructionFor": 88.4,
      "destructionAgainst": 66.93333333333334,
      "opponent": {
        "tag": "#9QRQR8GY",
        "name": "Master_Killers",
        "clanLevel": 22
      }
    }
  ],
  "roster": [
    {
      "tag": "#L8GVJ2JCC",
      "name": "Zestrzelony",
      "townHallLevel": 14,
      "attacks": 7,
      "stars": 20,
      "destruction": 686,
      "triples": 6,
      "bestDestruction": 100,
      "avgStars": 2.857142857142857,
      "avgDestruction": 98,
      "warsParticipated": 7,
      "missedAttacks": 0,
      "zeroStars": 0,
      "oneStars": 0,
      "twoStars": 1,
      "durationTotal": 889,
      "durationSamples": 7,
      "avgDuration": 127,
      "bestAttack": {
        "stars": 3,
        "destruction": 100,
        "duration": 88
      },
      "threeStarRate": 85.71428571428571,
      "reliabilityScore": 100,
      "timesAttacked": 6,
      "starsAllowed": 15,
      "avgStarsAllowed": 2.5,
      "triplesAllowed": 4,
      "defenseQuality": 16.67
    },
    {
      "tag": "#QQJ0GRRG",
      "name": "Skz",
      "townHallLevel": 16,
      "attacks": 7,
      "stars": 19,
      "destruction": 672,
      "triples": 6,
      "bestDestruction": 100,
      "avgStars": 2.7142857142857144,
      "avgDestruction": 96,
      "warsParticipated": 7,
      "missedAttacks": 0,
      "zeroStars": 0,
      "oneStars": 1,
      "twoStars": 0,
      "durationTotal": 861,
      "durationSamples": 7,
      "avgDuration": 123,
      "bestAttack": {
        "stars": 3,
        "destruction": 100,
        "duration": 111
      },
      "threeStarRate": 85.71428571428571,
      "reliabilityScore": 100,
      "timesAttacked": 6,
      "starsAllowed": 9,
      "avgStarsAllowed": 1.5,
      "triplesAllowed": 0,
      "defenseQuality": 50
    },
    {
      "tag": "#29LYGGPLR",
      "name": "Zhero",
      "townHallLevel": 16,
      "attacks": 7,
      "stars": 19,
      "destruction": 687,
      "triples": 6,
      "bestDestruction": 100,
      "avgStars": 2.7142857142857144,
      "avgDestruction": 98.14285714285714,
      "warsParticipated": 7,
      "missedAttacks": 0,
      "zeroStars": 0,
      "oneStars": 1,
      "twoStars": 0,
      "durationTotal": 769,
      "durationSamples": 7,
      "avgDuration": 109.85714285714286,
      "bestAttack": {
        "stars": 3,
        "destruction": 100,
        "duration": 70
      },
      "threeStarRate": 85.71428571428571,
      "reliabilityScore": 100,
      "timesAttacked": 5,
      "starsAllowed": 10,
      "avgStarsAllowed": 2,
      "triplesAllowed": 1,
      "defenseQuality": 33.33
    },
    {
      "tag": "#RCVCYVYJ",
      "name": "Kmmanutd",
      "townHallLevel": 14,
      "attacks": 7,
      "stars": 19,
      "destruction": 672,
      "triples": 5,
      "bestDestruction": 100,
      "avgStars": 2.7142857142857144,
      "avgDestruction": 96,
      "warsParticipated": 7,
      "missedAttacks": 0,
      "zeroStars": 0,
      "oneStars": 0,
      "twoStars": 2,
      "durationTotal": 783,
      "durationSamples": 7,
      "avgDuration": 111.85714285714286,
      "bestAttack": {
        "stars": 3,
        "destruction": 100,
        "duration": 60
      },
      "threeStarRate": 71.42857142857143,
      "reliabilityScore": 100,
      "timesAttacked": 4,
      "starsAllowed": 10,
      "avgStarsAllowed": 2.5,
      "triplesAllowed": 2,
      "defenseQuality": 16.67
    },
    {
      "tag": "#YR8YQ02GL",
      "name": "Fi3ipeQ",
      "townHallLevel": 14,
      "attacks": 7,
      "stars": 19,
      "destruction": 674,
      "triples": 5,
      "bestDestruction": 100,
      "avgStars": 2.7142857142857144,
      "avgDestruction": 96.28571428571429,
      "warsParticipated": 7,
      "missedAttacks": 0,
      "zeroStars": 0,
      "oneStars": 0,
      "twoStars": 2,
      "durationTotal": 738,
      "durationSamples": 7,
      "avgDuration": 105.42857142857143,
      "bestAttack": {
        "stars": 3,
        "destruction": 100,
        "duration": 60
      },
      "threeStarRate": 71.42857142857143,
      "reliabilityScore": 100,
      "timesAttacked": 6,
      "starsAllowed": 16,
      "avgStarsAllowed": 2.67,
      "triplesAllowed": 4,
      "defenseQuality": 11.11
    },
    {
      "tag": "#LLP0802P9",
      "name": "Aigor",
      "townHallLevel": 15,
      "attacks": 7,
      "stars": 18,
      "destruction": 654,
      "triples": 4,
      "bestDestruction": 100,
      "avgStars": 2.5714285714285716,
      "avgDestruction": 93.42857142857143,
      "warsParticipated": 7,
      "missedAttacks": 0,
      "zeroStars": 0,
      "oneStars": 0,
      "twoStars": 3,
      "durationTotal": 983,
      "durationSamples": 7,
      "avgDuration": 140.42857142857142,
      "bestAttack": {
        "stars": 3,
        "destruction": 100,
        "duration": 113
      },
      "threeStarRate": 57.14285714285714,
      "reliabilityScore": 100,
      "timesAttacked": 6,
      "starsAllowed": 11,
      "avgStarsAllowed": 1.83,
      "triplesAllowed": 2,
      "defenseQuality": 38.89
    },
    {
      "tag": "#UGLCL0",
      "name": "Jaysaq",
      "townHallLevel": 14,
      "attacks": 7,
      "stars": 18,
      "destruction": 645,
      "triples": 4,
      "bestDestruction": 100,
      "avgStars": 2.5714285714285716,
      "avgDestruction": 92.14285714285714,
      "warsParticipated": 7,
      "missedAttacks": 0,
      "zeroStars": 0,
      "oneStars": 0,
      "twoStars": 3,
      "durationTotal": 919,
      "durationSamples": 7,
      "avgDuration": 131.28571428571428,
      "bestAttack": {
        "stars": 3,
        "destruction": 100,
        "duration": 106
      },
      "threeStarRate": 57.14285714285714,
      "reliabilityScore": 100,
      "timesAttacked": 6,
      "starsAllowed": 12,
      "avgStarsAllowed": 2,
      "triplesAllowed": 2,
      "defenseQuality": 33.33
    },
    {
      "tag": "#G98Q9VC0L",
      "name": "floymaster",
      "townHallLevel": 14,
      "attacks": 7,
      "stars": 16,
      "destruction": 616,
      "triples": 3,
      "bestDestruction": 100,
      "avgStars": 2.2857142857142856,
      "avgDestruction": 88,
      "warsParticipated": 7,
      "missedAttacks": 0,
      "zeroStars": 0,
      "oneStars": 1,
      "twoStars": 3,
      "durationTotal": 729,
      "durationSamples": 7,
      "avgDuration": 104.14285714285714,
      "bestAttack": {
        "stars": 3,
        "destruction": 100,
        "duration": 67
      },
      "threeStarRate": 42.857142857142854,
      "reliabilityScore": 100,
      "timesAttacked": 6,
      "starsAllowed": 10,
      "avgStarsAllowed": 1.67,
      "triplesAllowed": 1,
      "defenseQuality": 44.44
    },
    {
      "tag": "#L90QVUQJ",
      "name": "Mamcorz",
      "townHallLevel": 16,
      "attacks": 7,
      "stars": 15,
      "destruction": 577,
      "triples": 2,
      "bestDestruction": 100,
      "avgStars": 2.142857142857143,
      "avgDestruction": 82.42857142857143,
      "warsParticipated": 7,
      "missedAttacks": 0,
      "zeroStars": 0,
      "oneStars": 1,
      "twoStars": 4,
      "durationTotal": 636,
      "durationSamples": 7,
      "avgDuration": 90.85714285714286,
      "bestAttack": {
        "stars": 3,
        "destruction": 100,
        "duration": 94
      },
      "threeStarRate": 28.57142857142857,
      "reliabilityScore": 100,
      "timesAttacked": 6,
      "starsAllowed": 12,
      "avgStarsAllowed": 2,
      "triplesAllowed": 0,
      "defenseQuality": 33.33
    },
    {
      "tag": "#2Q0CPLQYC",
      "name": "KrisVanB",
      "townHallLevel": 17,
      "attacks": 7,
      "stars": 14,
      "destruction": 572,
      "triples": 0,
      "bestDestruction": 96,
      "avgStars": 2,
      "avgDestruction": 81.71428571428571,
      "warsParticipated": 7,
      "missedAttacks": 0,
      "zeroStars": 0,
      "oneStars": 0,
      "twoStars": 7,
      "durationTotal": 617,
      "durationSamples": 7,
      "avgDuration": 88.14285714285714,
      "bestAttack": {
        "stars": 2,
        "destruction": 96,
        "duration": 135
      },
      "threeStarRate": 0,
      "reliabilityScore": 100,
      "timesAttacked": 5,
      "starsAllowed": 11,
      "avgStarsAllowed": 2.2,
      "triplesAllowed": 1,
      "defenseQuality": 26.67
    },
    {
      "tag": "#YY0JU98Q0",
      "name": "DEADPOOL",
      "townHallLevel": 15,
      "attacks": 7,
      "stars": 14,
      "destruction": 497,
      "triples": 1,
      "bestDestruction": 100,
      "avgStars": 2,
      "avgDestruction": 71,
      "warsParticipated": 7,
      "missedAttacks": 0,
      "zeroStars": 0,
      "oneStars": 1,
      "twoStars": 5,
      "durationTotal": 709,
      "durationSamples": 7,
      "avgDuration": 101.28571428571429,
      "bestAttack": {
        "stars": 3,
        "destruction": 100,
        "duration": 89
      },
      "threeStarRate": 14.285714285714285,
      "reliabilityScore": 100,
      "timesAttacked": 5,
      "starsAllowed": 13,
      "avgStarsAllowed": 2.6,
      "triplesAllowed": 3,
      "defenseQuality": 13.33
    },
    {
      "tag": "#RGGG99UJ",
      "name": "Voga",
      "townHallLevel": 17,
      "attacks": 7,
      "stars": 13,
      "destruction": 458,
      "triples": 0,
      "bestDestruction": 83,
      "avgStars": 1.8571428571428572,
      "avgDestruction": 65.42857142857143,
      "warsParticipated": 7,
      "missedAttacks": 0,
      "zeroStars": 0,
      "oneStars": 1,
      "twoStars": 6,
      "durationTotal": 914,
      "durationSamples": 7,
      "avgDuration": 130.57142857142858,
      "bestAttack": {
        "stars": 2,
        "destruction": 83,
        "duration": 171
      },
      "threeStarRate": 0,
      "reliabilityScore": 100,
      "timesAttacked": 5,
      "starsAllowed": 10,
      "avgStarsAllowed": 2,
      "triplesAllowed": 1,
      "defenseQuality": 33.33
    },
    {
      "tag": "#8PVPQGLU9",
      "name": "Lemoniadek",
      "townHallLevel": 14,
      "attacks": 5,
      "stars": 13,
      "destruction": 477,
      "triples": 3,
      "bestDestruction": 100,
      "avgStars": 2.6,
      "avgDestruction": 95.4,
      "warsParticipated": 5,
      "missedAttacks": 0,
      "zeroStars": 0,
      "oneStars": 0,
      "twoStars": 2,
      "durationTotal": 620,
      "durationSamples": 5,
      "avgDuration": 124,
      "bestAttack": {
        "stars": 3,
        "destruction": 100,
        "duration": 86
      },
      "threeStarRate": 60,
      "reliabilityScore": 100,
      "timesAttacked": 5,
      "starsAllowed": 11,
      "avgStarsAllowed": 2.2,
      "triplesAllowed": 1,
      "defenseQuality": 26.67
    },
    {
      "tag": "#2VPJ8G0PP",
      "name": "fl0w",
      "townHallLevel": 16,
      "attacks": 5,
      "stars": 12,
      "destruction": 415,
      "triples": 2,
      "bestDestruction": 100,
      "avgStars": 2.4,
      "avgDestruction": 83,
      "warsParticipated": 6,
      "missedAttacks": 1,
      "zeroStars": 0,
      "oneStars": 0,
      "twoStars": 3,
      "durationTotal": 755,
      "durationSamples": 5,
      "avgDuration": 151,
      "bestAttack": {
        "stars": 3,
        "destruction": 100,
        "duration": 95
      },
      "threeStarRate": 40,
      "reliabilityScore": 83.33333333333334,
      "timesAttacked": 4,
      "starsAllowed": 3,
      "avgStarsAllowed": 0.75,
      "triplesAllowed": 0,
      "defenseQuality": 75
    },
    {
      "tag": "#QLJ20JYUR",
      "name": "Maciaspopskhr_",
      "townHallLevel": 13,
      "attacks": 4,
      "stars": 12,
      "destruction": 400,
      "triples": 4,
      "bestDestruction": 100,
      "avgStars": 3,
      "avgDestruction": 100,
      "warsParticipated": 4,
      "missedAttacks": 0,
      "zeroStars": 0,
      "oneStars": 0,
      "twoStars": 0,
      "durationTotal": 287,
      "durationSamples": 4,
      "avgDuration": 71.75,
      "bestAttack": {
        "stars": 3,
        "destruction": 100,
        "duration": 60
      },
      "threeStarRate": 100,
      "reliabilityScore": 100,
      "timesAttacked": 4,
      "starsAllowed": 9,
      "avgStarsAllowed": 2.25,
      "triplesAllowed": 1,
      "defenseQuality": 25
    },
    {
      "tag": "#PUY8YP9J2",
      "name": "Pieczarka",
      "townHallLevel": 14,
      "attacks": 4,
      "stars": 11,
      "destruction": 392,
      "triples": 3,
      "bestDestruction": 100,
      "avgStars": 2.75,
      "avgDestruction": 98,
      "warsParticipated": 4,
      "missedAttacks": 0,
      "zeroStars": 0,
      "oneStars": 0,
      "twoStars": 1,
      "durationTotal": 541,
      "durationSamples": 4,
      "avgDuration": 135.25,
      "bestAttack": {
        "stars": 3,
        "destruction": 100,
        "duration": 92
      },
      "threeStarRate": 75,
      "reliabilityScore": 100,
      "timesAttacked": 3,
      "starsAllowed": 7,
      "avgStarsAllowed": 2.33,
      "triplesAllowed": 1,
      "defenseQuality": 22.22
    },
    {
      "tag": "#2J2PQV9LU",
      "name": "AKIL",
      "townHallLevel": 13,
      "attacks": 1,
      "stars": 2,
      "destruction": 99,
      "triples": 0,
      "bestDestruction": 99,
      "avgStars": 2,
      "avgDestruction": 99,
      "warsParticipated": 1,
      "missedAttacks": 0,
      "zeroStars": 0,
      "oneStars": 0,
      "twoStars": 1,
      "durationTotal": 180,
      "durationSamples": 1,
      "avgDuration": 180,
      "bestAttack": {
        "stars": 2,
        "destruction": 99,
        "duration": 180
      },
      "threeStarRate": 0,
      "reliabilityScore": 100,
      "timesAttacked": 0,
      "starsAllowed": 0,
      "avgStarsAllowed": 0,
      "triplesAllowed": 0,
      "defenseQuality": 100
    },
    {
      "tag": "#YJ0YC229",
      "name": "andre",
      "townHallLevel": 15,
      "attacks": 0,
      "stars": 0,
      "destruction": 0,
      "triples": 0,
      "bestDestruction": 0,
      "avgStars": 0,
      "avgDestruction": 0,
      "warsParticipated": 1,
      "missedAttacks": 1,
      "zeroStars": 0,
      "oneStars": 0,
      "twoStars": 0,
      "bestAttack": {
        "stars": 0,
        "destruction": 0
      },
      "threeStarRate": 0,
      "reliabilityScore": 0,
      "timesAttacked": 1,
      "starsAllowed": 2,
      "avgStarsAllowed": 2,
      "triplesAllowed": 0,
      "defenseQuality": 33.33
    }
  ]
}