{
  "generatedAt": "2026-02-27T06:16:01.679Z",
  "season": "2025-10",
  "warTag": "P0J2J8GJ-20251007T234238000Z",
  "startTime": "20251006T223521.000Z",
  "endTime": "20251007T234238.000Z",
  "teamSize": 15,
  "result": "win",
  "clan": {
    "tag": "#P0J2J8GJ",
    "name": "coc masters PL",
    "clanLevel": 29,
    "stars": 44,
    "destructionPercentage": 99.73333333333333,
    "attacks": 15,
    "members": [
      {
        "tag": "#L999C9G8",
        "name": "Maryśka™",
        "townhallLevel": 17,
        "mapPosition": 1,
        "attacks": [
          {
            "attackerTag": "#L999C9G8",
            "attackerName": "Maryśka™",
            "attackerTH": 17,
            "attackerMapPosition": 1,
            "defenderTag": "#9RCRG0GYL",
            "defenderName": "الحميضه",
            "defenderTH": 17,
            "defenderMapPosition": 1,
            "stars": 3,
            "destructionPercentage": 100,
            "duration": 144,
            "order": 2,
            "side": "clan"
          }
        ],
        "stars": 3,
        "destruction": 100,
        "opponentAttacks": 1,
        "bestOpponentAttack": {
          "stars": 2,
          "destructionPercentage": 80,
          "attackerName": "الحميضه"
        }
      },
      {
        "tag": "#YPG8QQ280",
        "name": "King Motyl",
        "townhallLevel": 17,
        "mapPosition": 2,
        "attacks": [
          {
            "attackerTag": "#YPG8QQ280",
            "attackerName": "King Motyl",
            "attackerTH": 17,
            "attackerMapPosition": 2,
            "defenderTag": "#P809PGRVJ",
            "defenderName": "المهيب ١١١",
            "defenderTH": 17,
            "defenderMapPosition": 8,
            "stars": 3,
            "destructionPercentage": 100,
            "duration": 162,
            "order": 11,
            "side": "clan"
          }
        ],
        "stars": 3,
        "destruction": 100,
        "opponentAttacks": 1,
        "bestOpponentAttack": {
          "stars": 2,
          "destructionPercentage": 93,
          "attackerName": "القائد"
        }
      },
      {
        "tag": "#2P9J8CCQY",
        "name": "Drax90",
        "townhallLevel": 17,
        "mapPosition": 3,
        "attacks": [
          {
            "attackerTag": "#2P9J8CCQY",
            "attackerName": "Drax90",
            "attackerTH": 17,
            "attackerMapPosition": 3,
            "defenderTag": "#9LVLPGRVP",
            "defenderName": "القائد",
            "defenderTH": 17,
            "defenderMapPosition": 9,
            "stars": 3,
            "destructionPercentage": 100,
            "duration": 164,
            "order": 12,
            "side": "clan"
          }
        ],
        "stars": 3,
        "destruction": 100,
        "opponentAttacks": 1,
        "bestOpponentAttack": {
          "stars": 3,
          "destructionPercentage": 100,
          "attackerName": "المهيب"
        }
      },
      {
        "tag": "#22Y9JQYJ",
        "name": "~ Yakuu ~",
        "townhallLevel": 17,
        "mapPosition": 4,
        "attacks": [
          {
            "attackerTag": "#22Y9JQYJ",
            "attackerName": "~ Yakuu ~",
            "attackerTH": 17,
            "attackerMapPosition": 4,
            "defenderTag": "#9JQ2VG8LR",
            "defenderName": "ابومحمد",
            "defenderTH": 17,
            "defenderMapPosition": 5,
            "stars": 3,
            "destructionPercentage": 100,
            "duration": 159,
            "order": 10,
            "side": "clan"
          }
        ],
        "stars": 3,
        "destruction": 100,
        "opponentAttacks": 1,
        "bestOpponentAttack": {
          "stars": 2,
          "destructionPercentage": 91,
          "attackerName": "المهيب ١١١"
        }
      },
      {
        "tag": "#LP2P2L002",
        "name": "wscielky bili",
        "townhallLevel": 17,
        "mapPosition": 5,
        "attacks": [
          {
            "attackerTag": "#LP2P2L002",
            "attackerName": "wscielky bili",
            "attackerTH": 17,
            "attackerMapPosition": 5,
            "defenderTag": "#29CRPGRPQ",
            "defenderName": "بروك ليسنر",
            "defenderTH": 17,
            "defenderMapPosition": 4,
            "stars": 3,
            "destructionPercentage": 100,
            "duration": 171,
            "order": 15,
            "side": "clan"
          }
        ],
        "stars": 3,
        "destruction": 100,
        "opponentAttacks": 1,
        "bestOpponentAttack": {
          "stars": 2,
          "destructionPercentage": 87,
          "attackerName": "⭐قصه حزن⭐"
        }
      },
      {
        "tag": "#22L2VVJQQ",
        "name": "Gantz",
        "townhallLevel": 17,
        "mapPosition": 6,
        "attacks": [
          {
            "attackerTag": "#22L2VVJQQ",
            "attackerName": "Gantz",
            "attackerTH": 17,
            "attackerMapPosition": 6,
            "defenderTag": "#2Y00YVJLL",
            "defenderName": "مـؖلهمᴾᵁFALA7 .",
            "defenderTH": 17,
            "defenderMapPosition": 7,
            "stars": 3,
            "destructionPercentage": 100,
            "duration": 126,
            "order": 7,
            "side": "clan"
          }
        ],
        "stars": 3,
        "destruction": 100,
        "opponentAttacks": 1,
        "bestOpponentAttack": {
          "stars": 2,
          "destructionPercentage": 83,
          "attackerName": "HAITHEM ALGBRTI"
        }
      },
      {
        "tag": "#802R9V99J",
        "name": "Pedro",
        "townhallLevel": 17,
        "mapPosition": 7,
        "attacks": [
          {
            "attackerTag": "#802R9V99J",
            "attackerName": "Pedro",
            "attackerTH": 17,
            "attackerMapPosition": 7,
            "defenderTag": "#YPYYV2LLJ",
            "defenderName": "ابو يأسر المحلي",
            "defenderTH": 17,
            "defenderMapPosition": 2,
            "stars": 3,
            "destructionPercentage": 100,
            "duration": 176,
            "order": 5,
            "side": "clan"
          }
        ],
        "stars": 3,
        "destruction": 100,
        "opponentAttacks": 1,
        "bestOpponentAttack": {
          "stars": 3,
          "destructionPercentage": 100,
          "attackerName": "علي، العولقي"
        }
      },
      {
        "tag": "#L90QVUQJ",
        "name": "Mamcorz",
        "townhallLevel": 17,
        "mapPosition": 8,
        "attacks": [
          {
            "attackerTag": "#L90QVUQJ",
            "attackerName": "Mamcorz",
            "attackerTH": 17,
            "attackerMapPosition": 8,
            "defenderTag": "#9U22PQPCL",
            "defenderName": "المهيب",
            "defenderTH": 17,
            "defenderMapPosition": 12,
            "stars": 3,
            "destructionPercentage": 100,
            "duration": 154,
            "order": 14,
            "side": "clan"
          }
        ],
        "stars": 3,
        "destruction": 100,
        "opponentAttacks": 1,
        "bestOpponentAttack": {
          "stars": 2,
          "destructionPercentage": 87,
          "attackerName": "بربروس"
        }
      },
      {
        "tag": "#2RUYVJJU",
        "name": "Zzlevo",
        "townhallLevel": 17,
        "mapPosition": 9,
        "attacks": [
          {
            "attackerTag": "#2RUYVJJU",
            "attackerName": "Zzlevo",
            "attackerTH": 17,
            "attackerMapPosition": 9,
            "defenderTag": "#PPGP98QVV",
            "defenderName": "الزعيم القائد",
            "defenderTH": 17,
            "defenderMapPosition": 6,
            "stars": 3,
            "destructionPercentage": 100,
            "duration": 179,
            "order": 8,
            "side": "clan"
          }
        ],
        "stars": 3,
        "destruction": 100,
        "opponentAttacks": 1,
        "bestOpponentAttack": {
          "stars": 2,
          "destructionPercentage": 91,
          "attackerName": "ابو يأسر المحلي"
        }
      },
      {
        "tag": "#PPRLRRUGU",
        "name": "inoja",
        "townhallLevel": 17,
        "mapPosition": 12,
        "attacks": [
          {
            "attackerTag": "#PPRLRRUGU",
            "attackerName": "inoja",
            "attackerTH": 17,
            "attackerMapPosition": 12,
            "defenderTag": "#9V2PYRQVJ",
            "defenderName": "بربروس",
            "defenderTH": 17,
            "defenderMapPosition": 10,
            "stars": 3,
            "destructionPercentage": 100,
            "duration": 149,
            "order": 6,
            "side": "clan"
          }
        ],
        "stars": 3,
        "destruction": 100,
        "opponentAttacks": 1,
        "bestOpponentAttack": {
          "stars": 2,
          "destructionPercentage": 87,
          "attackerName": "ابومحمد"
        }
      },
      {
        "tag": "#299PCL828",
        "name": "Wybraniec",
        "townhallLevel": 17,
        "mapPosition": 13,
        "attacks": [
          {
            "attackerTag": "#299PCL828",
            "attackerName": "Wybraniec",
            "attackerTH": 17,
            "attackerMapPosition": 13,
            "defenderTag": "#PPGRQQL98",
            "defenderName": "علي، العولقي",
            "defenderTH": 17,
            "defenderMapPosition": 11,
            "stars": 2,
            "destructionPercentage": 96,
            "duration": 145,
            "order": 9,
            "side": "clan"
          }
        ],
        "stars": 2,
        "destruction": 96,
        "opponentAttacks": 1,
        "bestOpponentAttack": {
          "stars": 2,
          "destructionPercentage": 91,
          "attackerName": "الزعيم القائد"
        }
      },
      {
        "tag": "#22CVU8U9",
        "name": "Jjiraya",
        "townhallLevel": 17,
        "mapPosition": 14,
        "attacks": [
          {
            "attackerTag": "#22CVU8U9",
            "attackerName": "Jjiraya",
            "attackerTH": 17,
            "attackerMapPosition": 14,
            "defenderTag": "#80V89QQGC",
            "defenderName": "حاول تهداء",
            "defenderTH": 17,
            "defenderMapPosition": 13,
            "stars": 3,
            "destructionPercentage": 100,
            "duration": 131,
            "order": 13,
            "side": "clan"
          }
        ],
        "stars": 3,
        "destruction": 100,
        "opponentAttacks": 1,
        "bestOpponentAttack": {
          "stars": 3,
          "destructionPercentage": 100,
          "attackerName": "بروك ليسنر"
        }
      },
      {
        "tag": "#LLYQ90PGV",
        "name": "Methanolek™",
        "townhallLevel": 17,
        "mapPosition": 15,
        "attacks": [
          {
            "attackerTag": "#LLYQ90PGV",
            "attackerName": "Methanolek™",
            "attackerTH": 17,
            "attackerMapPosition": 15,
            "defenderTag": "#8RCR09V0C",
            "defenderName": "⭐قصه حزن⭐",
            "defenderTH": 17,
            "defenderMapPosition": 3,
            "stars": 3,
            "destructionPercentage": 100,
            "duration": 166,
            "order": 3,
            "side": "clan"
          }
        ],
        "stars": 3,
        "destruction": 100,
        "opponentAttacks": 1,
        "bestOpponentAttack": {
          "stars": 3,
          "destructionPercentage": 100,
          "attackerName": "مـؖلهمᴾᵁFALA7 ."
        }
      },
      {
        "tag": "#Y9UV2CCQ",
        "name": "Marek",
        "townhallLevel": 17,
        "mapPosition": 19,
        "attacks": [
          {
            "attackerTag": "#Y9UV2CCQ",
            "attackerName": "Marek",
            "attackerTH": 17,
            "attackerMapPosition": 19,
            "defenderTag": "#9JV2VCPYU",
            "defenderName": "HAITHEM ALGBRTI",
            "defenderTH": 17,
            "defenderMapPosition": 15,
            "stars": 3,
            "destructionPercentage": 100,
            "duration": 137,
            "order": 17,
            "side": "clan"
          }
        ],
        "stars": 3,
        "destruction": 100,
        "opponentAttacks": 1,
        "bestOpponentAttack": {
          "stars": 3,
          "destructionPercentage": 100,
          "attackerName": "YASEEN™✅"
        }
      },
      {
        "tag": "#YLJJYG28G",
        "name": "byczeq",
        "townhallLevel": 17,
        "mapPosition": 20,
        "attacks": [
          {
            "attackerTag": "#YLJJYG28G",
            "attackerName": "byczeq",
            "attackerTH": 17,
            "attackerMapPosition": 20,
            "defenderTag": "#PQVRV0L2U",
            "defenderName": "YASEEN™✅",
            "defenderTH": 17,
            "defenderMapPosition": 14,
            "stars": 3,
            "destructionPercentage": 100,
            "duration": 158,
            "order": 1,
            "side": "clan"
          }
        ],
        "stars": 3,
        "destruction": 100,
        "opponentAttacks": 1,
        "bestOpponentAttack": {
          "stars": 3,
          "destructionPercentage": 100,
          "attackerName": "حاول تهداء"
        }
      }
    ]
  },
  "opponent": {
    "tag": "#CJLGGC2U",
    "name": "مَلوِګ أّلَيمَن",
    "clanLevel": 24,
    "stars": 36,
    "destructionPercentage": 92.66666666666667,
    "attacks": 15,
    "members": [
      {
        "tag": "#9RCRG0GYL",
        "name": "الحميضه",
        "townhallLevel": 17,
        "mapPosition": 1,
        "attacks": [
          {
            "attackerTag": "#9RCRG0GYL",
            "attackerName": "الحميضه",
            "attackerTH": 17,
            "attackerMapPosition": 1,
            "defenderTag": "#L999C9G8",
            "defenderName": "Maryśka™",
            "defenderTH": 17,
            "defenderMapPosition": 1,
            "stars": 2,
            "destructionPercentage": 80,
            "duration": 132,
            "order": 23,
            "side": "opponent"
          }
        ],
        "stars": 2,
        "destruction": 80,
        "opponentAttacks": 1,
        "bestOpponentAttack": {
          "stars": 3,
          "destructionPercentage": 100,
          "attackerName": "Maryśka™"
        }
      },
      {
        "tag": "#YPYYV2LLJ",
        "name": "ابو يأسر المحلي",
        "townhallLevel": 17,
        "mapPosition": 2,
        "attacks": [
          {
            "attackerTag": "#YPYYV2LLJ",
            "attackerName": "ابو يأسر المحلي",
            "attackerTH": 17,
            "attackerMapPosition": 2,
            "defenderTag": "#2RUYVJJU",
            "defenderName": "Zzlevo",
            "defenderTH": 17,
            "defenderMapPosition": 9,
            "stars": 2,
            "destructionPercentage": 91,
            "duration": 128,
            "order": 25,
            "side": "opponent"
          }
        ],
        "stars": 2,
        "destruction": 91,
        "opponentAttacks": 1,
        "bestOpponentAttack": {
          "stars": 3,
          "destructionPercentage": 100,
          "attackerName": "Pedro"
        }
      },
      {
        "tag": "#8RCR09V0C",
        "name": "⭐قصه حزن⭐",
        "townhallLevel": 17,
        "mapPosition": 3,
        "attacks": [
          {
            "attackerTag": "#8RCR09V0C",
            "attackerName": "⭐قصه حزن⭐",
            "attackerTH": 17,
            "attackerMapPosition": 3,
            "defenderTag": "#LP2P2L002",
            "defenderName": "wscielky bili",
            "defenderTH": 17,
            "defenderMapPosition": 5,
            "stars": 2,
            "destructionPercentage": 87,
            "duration": 167,
            "order": 4,
            "side": "opponent"
          }
        ],
        "stars": 2,
        "destruction": 87,
        "opponentAttacks": 1,
        "bestOpponentAttack": {
          "stars": 3,
          "destructionPercentage": 100,
          "attackerName": "Methanolek™"
        }
      },
      {
        "tag": "#29CRPGRPQ",
        "name": "بروك ليسنر",
        "townhallLevel": 17,
        "mapPosition": 4,
        "attacks": [
          {
            "attackerTag": "#29CRPGRPQ",
            "attackerName": "بروك ليسنر",
            "attackerTH": 17,
            "attackerMapPosition": 4,
            "defenderTag": "#22CVU8U9",
            "defenderName": "Jjiraya",
            "defenderTH": 17,
            "defenderMapPosition": 14,
            "stars": 3,
            "destructionPercentage": 100,
            "duration": 147,
            "order": 27,
            "side": "opponent"
          }
        ],
        "stars": 3,
        "destruction": 100,
        "opponentAttacks": 1,
        "bestOpponentAttack": {
          "stars": 3,
          "destructionPercentage": 100,
          "attackerName": "wscielky bili"
        }
      },
      {
        "tag": "#9JQ2VG8LR",
        "name": "ابومحمد",
        "townhallLevel": 17,
        "mapPosition": 5,
        "attacks": [
          {
            "attackerTag": "#9JQ2VG8LR",
            "attackerName": "ابومحمد",
            "attackerTH": 17,
            "attackerMapPosition": 5,
            "defenderTag": "#PPRLRRUGU",
            "defenderName": "inoja",
            "defenderTH": 17,
            "defenderMapPosition": 12,
            "stars": 2,
            "destructionPercentage": 87,
            "duration": 158,
            "order": 26,
            "side": "opponent"
          }
        ],
        "stars": 2,
        "destruction": 87,
        "opponentAttacks": 1,
        "bestOpponentAttack": {
          "stars": 3,
          "destructionPercentage": 100,
          "attackerName": "~ Yakuu ~"
        }
      },
      {
        "tag": "#PPGP98QVV",
        "name": "الزعيم القائد",
        "townhallLevel": 17,
        "mapPosition": 6,
        "attacks": [
          {
            "attackerTag": "#PPGP98QVV",
            "attackerName": "الزعيم القائد",
            "attackerTH": 17,
            "attackerMapPosition": 6,
            "defenderTag": "#299PCL828",
            "defenderName": "Wybraniec",
            "defenderTH": 17,
            "defenderMapPosition": 13,
            "stars": 2,
            "destructionPercentage": 91,
            "duration": 138,
            "order": 28,
            "side": "opponent"
          }
        ],
        "stars": 2,
        "destruction": 91,
        "opponentAttacks": 1,
        "bestOpponentAttack": {
          "stars": 3,
          "destructionPercentage": 100,
          "attackerName": "Zzlevo"
        }
      },
      {
        "tag": "#2Y00YVJLL",
        "name": "مـؖلهمᴾᵁFALA7 .",
        "townhallLevel": 17,
        "mapPosition": 7,
        "attacks": [
          {
            "attackerTag": "#2Y00YVJLL",
            "attackerName": "مـؖلهمᴾᵁFALA7 .",
            "attackerTH": 17,
            "attackerMapPosition": 7,
            "defenderTag": "#LLYQ90PGV",
            "defenderName": "Methanolek™",
            "defenderTH": 17,
            "defenderMapPosition": 15,
            "stars": 3,
            "destructionPercentage": 100,
            "duration": 132,
            "order": 29,
            "side": "opponent"
          }
        ],
        "stars": 3,
        "destruction": 100,
        "opponentAttacks": 1,
        "bestOpponentAttack": {
          "stars": 3,
          "destructionPercentage": 100,
          "attackerName": "Gantz"
        }
      },
      {
        "tag": "#P809PGRVJ",
        "name": "المهيب ١١١",
        "townhallLevel": 17,
        "mapPosition": 8,
        "attacks": [
          {
            "attackerTag": "#P809PGRVJ",
            "attackerName": "المهيب ١١١",
            "attackerTH": 17,
            "attackerMapPosition": 8,
            "defenderTag": "#22Y9JQYJ",
            "defenderName": "~ Yakuu ~",
            "defenderTH": 17,
            "defenderMapPosition": 4,
            "stars": 2,
            "destructionPercentage": 91,
            "duration": 147,
            "order": 21,
            "side": "opponent"
          }
        ],
        "stars": 2,
        "destruction": 91,
        "opponentAttacks": 1,
        "bestOpponentAttack": {
          "stars": 3,
          "destructionPercentage": 100,
          "attackerName": "King Motyl"
        }
      },
      {
        "tag": "#9LVLPGRVP",
        "name": "القائد",
        "townhallLevel": 17,
        "mapPosition": 9,
        "attacks": [
          {
            "attackerTag": "#9LVLPGRVP",
            "attackerName": "القائد",
            "attackerTH": 17,
            "attackerMapPosition": 9,
            "defenderTag": "#YPG8QQ280",
            "defenderName": "King Motyl",
            "defenderTH": 17,
            "defenderMapPosition": 2,
            "stars": 2,
            "destructionPercentage": 93,
            "duration": 169,
            "order": 24,
            "side": "opponent"
          }
        ],
        "stars": 2,
        "destruction": 93,
        "opponentAttacks": 1,
        "bestOpponentAttack": {
          "stars": 3,
          "destructionPercentage": 100,
          "attackerName": "Drax90"
        }
      },
      {
        "tag": "#9V2PYRQVJ",
        "name": "بربروس",
        "townhallLevel": 17,
        "mapPosition": 10,
        "attacks": [
          {
            "attackerTag": "#9V2PYRQVJ",
            "attackerName": "بربروس",
            "attackerTH": 17,
            "attackerMapPosition": 10,
            "defenderTag": "#L90QVUQJ",
            "defenderName": "Mamcorz",
            "defenderTH": 17,
            "defenderMapPosition": 8,
            "stars": 2,
            "destructionPercentage": 87,
            "duration": 180,
            "order": 22,
            "side": "opponent"
          }
        ],
        "stars": 2,
        "destruction": 87,
        "opponentAttacks": 1,
        "bestOpponentAttack": {
          "stars": 3,
          "destructionPercentage": 100,
          "attackerName": "inoja"
        }
      },
      {
        "tag": "#PPGRQQL98",
        "name": "علي، العولقي",
        "townhallLevel": 17,
        "mapPosition": 11,
        "attacks": [
          {
            "attackerTag": "#PPGRQQL98",
            "attackerName": "علي، العولقي",
            "attackerTH": 17,
            "attackerMapPosition": 11,
            "defenderTag": "#802R9V99J",
            "defenderName": "Pedro",
            "defenderTH": 17,
            "defenderMapPosition": 7,
            "stars": 3,
            "destructionPercentage": 100,
            "duration": 143,
            "order": 19,
            "side": "opponent"
          }
        ],
        "stars": 3,
        "destruction": 100,
        "opponentAttacks": 1,
        "bestOpponentAttack": {
          "stars": 2,
          "destructionPercentage": 96,
          "attackerName": "Wybraniec"
        }
      },
      {
        "tag": "#9U22PQPCL",
        "name": "المهيب",
        "townhallLevel": 17,
        "mapPosition": 12,
        "attacks": [
          {
            "attackerTag": "#9U22PQPCL",
            "attackerName": "المهيب",
            "attackerTH": 17,
            "attackerMapPosition": 12,
            "defenderTag": "#2P9J8CCQY",
            "defenderName": "Drax90",
            "defenderTH": 17,
            "defenderMapPosition": 3,
            "stars": 3,
            "destructionPercentage": 100,
            "duration": 120,
            "order": 20,
            "side": "opponent"
          }
        ],
        "stars": 3,
        "destruction": 100,
        "opponentAttacks": 1,
        "bestOpponentAttack": {
          "stars": 3,
          "destructionPercentage": 100,
          "attackerName": "Mamcorz"
        }
      },
      {
        "tag": "#80V89QQGC",
        "name": "حاول تهداء",
        "townhallLevel": 17,
        "mapPosition": 13,
        "attacks": [
          {
            "attackerTag": "#80V89QQGC",
            "attackerName": "حاول تهداء",
            "attackerTH": 17,
            "attackerMapPosition": 13,
            "defenderTag": "#YLJJYG28G",
            "defenderName": "byczeq",
            "defenderTH": 17,
            "defenderMapPosition": 20,
            "stars": 3,
            "destructionPercentage": 100,
            "duration": 172,
            "order": 30,
            "side": "opponent"
          }
        ],
        "stars": 3,
        "destruction": 100,
        "opponentAttacks": 1,
        "bestOpponentAttack": {
          "stars": 3,
          "destructionPercentage": 100,
          "attackerName": "Jjiraya"
        }
      },
      {
        "tag": "#PQVRV0L2U",
        "name": "YASEEN™✅",
        "townhallLevel": 17,
        "mapPosition": 14,
        "attacks": [
          {
            "attackerTag": "#PQVRV0L2U",
            "attackerName": "YASEEN™✅",
            "attackerTH": 17,
            "attackerMapPosition": 14,
            "defenderTag": "#Y9UV2CCQ",
            "defenderName": "Marek",
            "defenderTH": 17,
            "defenderMapPosition": 19,
            "stars": 3,
            "destructionPercentage": 100,
            "duration": 173,
            "order": 16,
            "side": "opponent"
          }
        ],
        "stars": 3,
        "destruction": 100,
        "opponentAttacks": 1,
        "bestOpponentAttack": {
          "stars": 3,
          "destructionPercentage": 100,
          "attackerName": "byczeq"
        }
      },
      {
        "tag": "#9JV2VCPYU",
        "name": "HAITHEM ALGBRTI",
        "townhallLevel": 17,
        "mapPosition": 15,
        "attacks": [
          {
            "attackerTag": "#9JV2VCPYU",
            "attackerName": "HAITHEM ALGBRTI",
            "attackerTH": 17,
            "attackerMapPosition": 15,
            "defenderTag": "#22L2VVJQQ",
            "defenderName": "Gantz",
            "defenderTH": 17,
            "defenderMapPosition": 6,
            "stars": 2,
            "destructionPercentage": 83,
            "duration": 122,
            "order": 18,
            "side": "opponent"
          }
        ],
        "stars": 2,
        "destruction": 83,
        "opponentAttacks": 1,
        "bestOpponentAttack": {
          "stars": 3,
          "destructionPercentage": 100,
          "attackerName": "Marek"
        }
      }
    ]
  },
  "attackTimeline": [
    {
      "attackerTag": "#YLJJYG28G",
      "attackerName": "byczeq",
      "attackerTH": 17,
      "attackerMapPosition": 20,
      "defenderTag": "#PQVRV0L2U",
      "defenderName": "YASEEN™✅",
      "defenderTH": 17,
      "defenderMapPosition": 14,
      "stars": 3,
      "destructionPercentage": 100,
      "duration": 158,
      "order": 1,
      "side": "clan"
    },
    {
      "attackerTag": "#L999C9G8",
      "attackerName": "Maryśka™",
      "attackerTH": 17,
      "attackerMapPosition": 1,
      "defenderTag": "#9RCRG0GYL",
      "defenderName": "الحميضه",
      "defenderTH": 17,
      "defenderMapPosition": 1,
      "stars": 3,
      "destructionPercentage": 100,
      "duration": 144,
      "order": 2,
      "side": "clan"
    },
    {
      "attackerTag": "#LLYQ90PGV",
      "attackerName": "Methanolek™",
      "attackerTH": 17,
      "attackerMapPosition": 15,
      "defenderTag": "#8RCR09V0C",
      "defenderName": "⭐قصه حزن⭐",
      "defenderTH": 17,
      "defenderMapPosition": 3,
      "stars": 3,
      "destructionPercentage": 100,
      "duration": 166,
      "order": 3,
      "side": "clan"
    },
    {
      "attackerTag": "#8RCR09V0C",
      "attackerName": "⭐قصه حزن⭐",
      "attackerTH": 17,
      "attackerMapPosition": 3,
      "defenderTag": "#LP2P2L002",
      "defenderName": "wscielky bili",
      "defenderTH": 17,
      "defenderMapPosition": 5,
      "stars": 2,
      "destructionPercentage": 87,
      "duration": 167,
      "order": 4,
      "side": "opponent"
    },
    {
      "attackerTag": "#802R9V99J",
      "attackerName": "Pedro",
      "attackerTH": 17,
      "attackerMapPosition": 7,
      "defenderTag": "#YPYYV2LLJ",
      "defenderName": "ابو يأسر المحلي",
      "defenderTH": 17,
      "defenderMapPosition": 2,
      "stars": 3,
      "destructionPercentage": 100,
      "duration": 176,
      "order": 5,
      "side": "clan"
    },
    {
      "attackerTag": "#PPRLRRUGU",
      "attackerName": "inoja",
      "attackerTH": 17,
      "attackerMapPosition": 12,
      "defenderTag": "#9V2PYRQVJ",
      "defenderName": "بربروس",
      "defenderTH": 17,
      "defenderMapPosition": 10,
      "stars": 3,
      "destructionPercentage": 100,
      "duration": 149,
      "order": 6,
      "side": "clan"
    },
    {
      "attackerTag": "#22L2VVJQQ",
      "attackerName": "Gantz",
      "attackerTH": 17,
      "attackerMapPosition": 6,
      "defenderTag": "#2Y00YVJLL",
      "defenderName": "مـؖلهمᴾᵁFALA7 .",
      "defenderTH": 17,
      "defenderMapPosition": 7,
      "stars": 3,
      "destructionPercentage": 100,
      "duration": 126,
      "order": 7,
      "side": "clan"
    },
    {
      "attackerTag": "#2RUYVJJU",
      "attackerName": "Zzlevo",
      "attackerTH": 17,
      "attackerMapPosition": 9,
      "defenderTag": "#PPGP98QVV",
      "defenderName": "الزعيم القائد",
      "defenderTH": 17,
      "defenderMapPosition": 6,
      "stars": 3,
      "destructionPercentage": 100,
      "duration": 179,
      "order": 8,
      "side": "clan"
    },
    {
      "attackerTag": "#299PCL828",
      "attackerName": "Wybraniec",
      "attackerTH": 17,
      "attackerMapPosition": 13,
      "defenderTag": "#PPGRQQL98",
      "defenderName": "علي، العولقي",
      "defenderTH": 17,
      "defenderMapPosition": 11,
      "stars": 2,
      "destructionPercentage": 96,
      "duration": 145,
      "order": 9,
      "side": "clan"
    },
    {
      "attackerTag": "#22Y9JQYJ",
      "attackerName": "~ Yakuu ~",
      "attackerTH": 17,
      "attackerMapPosition": 4,
      "defenderTag": "#9JQ2VG8LR",
      "defenderName": "ابومحمد",
      "defenderTH": 17,
      "defenderMapPosition": 5,
      "stars": 3,
      "destructionPercentage": 100,
      "duration": 159,
      "order": 10,
      "side": "clan"
    },
    {
      "attackerTag": "#YPG8QQ280",
      "attackerName": "King Motyl",
      "attackerTH": 17,
      "attackerMapPosition": 2,
      "defenderTag": "#P809PGRVJ",
      "defenderName": "المهيب ١١١",
      "defenderTH": 17,
      "defenderMapPosition": 8,
      "stars": 3,
      "destructionPercentage": 100,
      "duration": 162,
      "order": 11,
      "side": "clan"
    },
    {
      "attackerTag": "#2P9J8CCQY",
      "attackerName": "Drax90",
      "attackerTH": 17,
      "attackerMapPosition": 3,
      "defenderTag": "#9LVLPGRVP",
      "defenderName": "القائد",
      "defenderTH": 17,
      "defenderMapPosition": 9,
      "stars": 3,
      "destructionPercentage": 100,
      "duration": 164,
      "order": 12,
      "side": "clan"
    },
    {
      "attackerTag": "#22CVU8U9",
      "attackerName": "Jjiraya",
      "attackerTH": 17,
      "attackerMapPosition": 14,
      "defenderTag": "#80V89QQGC",
      "defenderName": "حاول تهداء",
      "defenderTH": 17,
      "defenderMapPosition": 13,
      "stars": 3,
      "destructionPercentage": 100,
      "duration": 131,
      "order": 13,
      "side": "clan"
    },
    {
      "attackerTag": "#L90QVUQJ",
      "attackerName": "Mamcorz",
      "attackerTH": 17,
      "attackerMapPosition": 8,
      "defenderTag": "#9U22PQPCL",
      "defenderName": "المهيب",
      "defenderTH": 17,
      "defenderMapPosition": 12,
      "stars": 3,
      "destructionPercentage": 100,
      "duration": 154,
      "order": 14,
      "side": "clan"
    },
    {
      "attackerTag": "#LP2P2L002",
      "attackerName": "wscielky bili",
      "attackerTH": 17,
      "attackerMapPosition": 5,
      "defenderTag": "#29CRPGRPQ",
      "defenderName": "بروك ليسنر",
      "defenderTH": 17,
      "defenderMapPosition": 4,
      "stars": 3,
      "destructionPercentage": 100,
      "duration": 171,
      "order": 15,
      "side": "clan"
    },
    {
      "attackerTag": "#PQVRV0L2U",
      "attackerName": "YASEEN™✅",
      "attackerTH": 17,
      "attackerMapPosition": 14,
      "defenderTag": "#Y9UV2CCQ",
      "defenderName": "Marek",
      "defenderTH": 17,
      "defenderMapPosition": 19,
      "stars": 3,
      "destructionPercentage": 100,
      "duration": 173,
      "order": 16,
      "side": "opponent"
    },
    {
      "attackerTag": "#Y9UV2CCQ",
      "attackerName": "Marek",
      "attackerTH": 17,
      "attackerMapPosition": 19,
      "defenderTag": "#9JV2VCPYU",
      "defenderName": "HAITHEM ALGBRTI",
      "defenderTH": 17,
      "defenderMapPosition": 15,
      "stars": 3,
      "destructionPercentage": 100,
      "duration": 137,
      "order": 17,
      "side": "clan"
    },
    {
      "attackerTag": "#9JV2VCPYU",
      "attackerName": "HAITHEM ALGBRTI",
      "attackerTH": 17,
      "attackerMapPosition": 15,
      "defenderTag": "#22L2VVJQQ",
      "defenderName": "Gantz",
      "defenderTH": 17,
      "defenderMapPosition": 6,
      "stars": 2,
      "destructionPercentage": 83,
      "duration": 122,
      "order": 18,
      "side": "opponent"
    },
    {
      "attackerTag": "#PPGRQQL98",
      "attackerName": "علي، العولقي",
      "attackerTH": 17,
      "attackerMapPosition": 11,
      "defenderTag": "#802R9V99J",
      "defenderName": "Pedro",
      "defenderTH": 17,
      "defenderMapPosition": 7,
      "stars": 3,
      "destructionPercentage": 100,
      "duration": 143,
      "order": 19,
      "side": "opponent"
    },
    {
      "attackerTag": "#9U22PQPCL",
      "attackerName": "المهيب",
      "attackerTH": 17,
      "attackerMapPosition": 12,
      "defenderTag": "#2P9J8CCQY",
      "defenderName": "Drax90",
      "defenderTH": 17,
      "defenderMapPosition": 3,
      "stars": 3,
      "destructionPercentage": 100,
      "duration": 120,
      "order": 20,
      "side": "opponent"
    },
    {
      "attackerTag": "#P809PGRVJ",
      "attackerName": "المهيب ١١١",
      "attackerTH": 17,
      "attackerMapPosition": 8,
      "defenderTag": "#22Y9JQYJ",
      "defenderName": "~ Yakuu ~",
      "defenderTH": 17,
      "defenderMapPosition": 4,
      "stars": 2,
      "destructionPercentage": 91,
      "duration": 147,
      "order": 21,
      "side": "opponent"
    },
    {
      "attackerTag": "#9V2PYRQVJ",
      "attackerName": "بربروس",
      "attackerTH": 17,
      "attackerMapPosition": 10,
      "defenderTag": "#L90QVUQJ",
      "defenderName": "Mamcorz",
      "defenderTH": 17,
      "defenderMapPosition": 8,
      "stars": 2,
      "destructionPercentage": 87,
      "duration": 180,
      "order": 22,
      "side": "opponent"
    },
    {
      "attackerTag": "#9RCRG0GYL",
      "attackerName": "الحميضه",
      "attackerTH": 17,
      "attackerMapPosition": 1,
      "defenderTag": "#L999C9G8",
      "defenderName": "Maryśka™",
      "defenderTH": 17,
      "defenderMapPosition": 1,
      "stars": 2,
      "destructionPercentage": 80,
      "duration": 132,
      "order": 23,
      "side": "opponent"
    },
    {
      "attackerTag": "#9LVLPGRVP",
      "attackerName": "القائد",
      "attackerTH": 17,
      "attackerMapPosition": 9,
      "defenderTag": "#YPG8QQ280",
      "defenderName": "King Motyl",
      "defenderTH": 17,
      "defenderMapPosition": 2,
      "stars": 2,
      "destructionPercentage": 93,
      "duration": 169,
      "order": 24,
      "side": "opponent"
    },
    {
      "attackerTag": "#YPYYV2LLJ",
      "attackerName": "ابو يأسر المحلي",
      "attackerTH": 17,
      "attackerMapPosition": 2,
      "defenderTag": "#2RUYVJJU",
      "defenderName": "Zzlevo",
      "defenderTH": 17,
      "defenderMapPosition": 9,
      "stars": 2,
      "destructionPercentage": 91,
      "duration": 128,
      "order": 25,
      "side": "opponent"
    },
    {
      "attackerTag": "#9JQ2VG8LR",
      "attackerName": "ابومحمد",
      "attackerTH": 17,
      "attackerMapPosition": 5,
      "defenderTag": "#PPRLRRUGU",
      "defenderName": "inoja",
      "defenderTH": 17,
      "defenderMapPosition": 12,
      "stars": 2,
      "destructionPercentage": 87,
      "duration": 158,
      "order": 26,
      "side": "opponent"
    },
    {
      "attackerTag": "#29CRPGRPQ",
      "attackerName": "بروك ليسنر",
      "attackerTH": 17,
      "attackerMapPosition": 4,
      "defenderTag": "#22CVU8U9",
      "defenderName": "Jjiraya",
      "defenderTH": 17,
      "defenderMapPosition": 14,
      "stars": 3,
      "destructionPercentage": 100,
      "duration": 147,
      "order": 27,
      "side": "opponent"
    },
    {
      "attackerTag": "#PPGP98QVV",
      "attackerName": "الزعيم القائد",
      "attackerTH": 17,
      "attackerMapPosition": 6,
      "defenderTag": "#299PCL828",
      "defenderName": "Wybraniec",
      "defenderTH": 17,
      "defenderMapPosition": 13,
      "stars": 2,
      "destructionPercentage": 91,
      "duration": 138,
      "order": 28,
      "side": "opponent"
    },
    {
      "attackerTag": "#2Y00YVJLL",
      "attackerName": "مـؖلهمᴾᵁFALA7 .",
      "attackerTH": 17,
      "attackerMapPosition": 7,
      "defenderTag": "#LLYQ90PGV",
      "defenderName": "Methanolek™",
      "defenderTH": 17,
      "defenderMapPosition": 15,
      "stars": 3,
      "destructionPercentage": 100,
      "duration": 132,
      "order": 29,
      "side": "opponent"
    },
    {
      "attackerTag": "#80V89QQGC",
      "attackerName": "حاول تهداء",
      "attackerTH": 17,
      "attackerMapPosition": 13,
      "defenderTag": "#YLJJYG28G",
      "defenderName": "byczeq",
      "defenderTH": 17,
      "defenderMapPosition": 20,
      "stars": 3,
      "destructionPercentage": 100,
      "duration": 172,
      "order": 30,
      "side": "opponent"
    }
  ]
}